torchft/__init__.py
torchft/_test/diloco_trainer.py
torchft/_test/managed_work_test.py
torchft/_test_utils.py
torchft/_torchft.cpython-39-x86_64-linux-gnu.so
torchft/_torchft.pyi
torchft/checkpointing/__init__.py
torchft/checkpointing/_rwlock.py
torchft/checkpointing/_serialization.py
torchft/checkpointing/http_transport.py
torchft/checkpointing/http_transport_bench.py
torchft/checkpointing/http_transport_test.py
torchft/checkpointing/pg_transport.py
torchft/checkpointing/pg_transport_bench.py
torchft/checkpointing/pg_transport_test.py
torchft/checkpointing/rwlock_test.py
torchft/checkpointing/transport.py
torchft/checkpointing/transport_test.py
torchft/collectives.py
torchft/collectives_test.py
torchft/coordination.py
torchft/coordination_test.py
torchft/data.py
torchft/data_test.py
torchft/ddp.py
torchft/ddp_test.py
torchft/diloco_regression_test.py
torchft/examples/slurm/README.md
torchft/examples/slurm/punisher.py
torchft/examples/slurm/runner.py
torchft/fsdp_test.py
torchft/futures.py
torchft/futures_test.py
torchft/http.py
torchft/lighthouse_test.py
torchft/local_sgd.py
torchft/local_sgd_integ_test.py
torchft/local_sgd_test.py
torchft/manager.py
torchft/manager_integ_test.py
torchft/manager_test.py
torchft/multiprocessing.py
torchft/multiprocessing_dummy_context.py
torchft/multiprocessing_test.py
torchft/optim.py
torchft/optim_test.py
torchft/otel.py
torchft/parameter_server.py
torchft/parameter_server_test.py
torchft/process_group.py
torchft/process_group_test.py
torchft/quantization.py
torchft/quantization_test.py
torchft/torchx.py
torchft/utils.py
torchft/work.py
torchft_nightly-2026.2.1.dist-info/METADATA
torchft_nightly-2026.2.1.dist-info/WHEEL
torchft_nightly-2026.2.1.dist-info/entry_points.txt
torchft_nightly-2026.2.1.dist-info/licenses/LICENSE
torchft_nightly-2026.2.1.dist-info/RECORD
