Metadata-Version: 2.4
Name: torchft-nightly
Version: 2026.2.1
Classifier: Programming Language :: Rust
Classifier: Programming Language :: Python :: Implementation :: CPython
Classifier: Programming Language :: Python :: Implementation :: PyPy
Requires-Dist: torch>=2.7
Requires-Dist: opentelemetry-exporter-otlp-proto-http>=1.39.0
Requires-Dist: opentelemetry-sdk>=1.39.0
Requires-Dist: opentelemetry-api>=1.39.0
Requires-Dist: pytest==8.3.4 ; extra == 'dev'
Requires-Dist: pytest-timeout ; extra == 'dev'
Requires-Dist: parameterized ; extra == 'dev'
Requires-Dist: expecttest ; extra == 'dev'
Requires-Dist: numpy ; extra == 'dev'
Requires-Dist: torchx-nightly ; extra == 'dev'
Requires-Dist: lintrunner ; extra == 'dev'
Requires-Dist: lintrunner-adapters ; extra == 'dev'
Provides-Extra: dev
License-File: LICENSE
Requires-Python: >=3.8
Project-URL: Documentation, https://docs.pytorch.org/torchft
Project-URL: Issues, https://github.com/pytorch/torchft/issues
Project-URL: Repository, https://github.com/pytorch/torchft
